pds/__init__.py
pds/registrysweepers/VERSION.txt
pds/registrysweepers/__init__.py
pds/registrysweepers/driver.py
pds/registrysweepers/ancestry/__init__.py
pds/registrysweepers/ancestry/ancestryrecord.py
pds/registrysweepers/ancestry/constants.py
pds/registrysweepers/ancestry/generation.py
pds/registrysweepers/ancestry/main.py
pds/registrysweepers/ancestry/productupdaterecord.py
pds/registrysweepers/ancestry/queries.py
pds/registrysweepers/ancestry/runtimeconstants.py
pds/registrysweepers/ancestry/typedefs.py
pds/registrysweepers/ancestry/utils.py
pds/registrysweepers/ancestry/versioning.py
pds/registrysweepers/legacy_registry_sync/__init__.py
pds/registrysweepers/legacy_registry_sync/legacy_registry_sync.py
pds/registrysweepers/legacy_registry_sync/opensearch_loaded_product.py
pds/registrysweepers/legacy_registry_sync/solr_doc_export_to_opensearch.py
pds/registrysweepers/provenance/__init__.py
pds/registrysweepers/provenance/constants.py
pds/registrysweepers/provenance/provenancerecord.py
pds/registrysweepers/provenance/versioning.py
pds/registrysweepers/reindexer/__init__.py
pds/registrysweepers/reindexer/constants.py
pds/registrysweepers/reindexer/main.py
pds/registrysweepers/repairkit/__init__.py
pds/registrysweepers/repairkit/allarrays.py
pds/registrysweepers/repairkit/versioning.py
pds/registrysweepers/utils/__init__.py
pds/registrysweepers/utils/majorminorversion.py
pds/registrysweepers/utils/misc.py
pds/registrysweepers/utils/bigdict/__init__.py
pds/registrysweepers/utils/bigdict/autodict.py
pds/registrysweepers/utils/bigdict/base.py
pds/registrysweepers/utils/bigdict/dictdict.py
pds/registrysweepers/utils/bigdict/spilldict.py
pds/registrysweepers/utils/bigdict/sqlite3dict.py
pds/registrysweepers/utils/db/__init__.py
pds/registrysweepers/utils/db/client.py
pds/registrysweepers/utils/db/indexing.py
pds/registrysweepers/utils/db/multitenancy.py
pds/registrysweepers/utils/db/update.py
pds/registrysweepers/utils/productidentifiers/__init__.py
pds_registry_sweepers-1.6.2.dist-info/licenses/LICENSE.md
pds_registry_sweepers-1.6.2.dist-info/licenses/NOTICE.txt
pds_registry_sweepers-1.6.2.dist-info/METADATA
pds_registry_sweepers-1.6.2.dist-info/WHEEL
pds_registry_sweepers-1.6.2.dist-info/entry_points.txt
pds_registry_sweepers-1.6.2.dist-info/top_level.txt
pds_registry_sweepers-1.6.2.dist-info/zip-safe
pds_registry_sweepers-1.6.2.dist-info/RECORD
