Metadata-Version: 2.4
Name: pds.registry-sweepers
Version: 1.6.2
Summary: A set of utility scripts which transform/augment PDS registry metadata to support additional capabilities.
Home-page: https://github.com/NASA-PDS/registry-sweepers
Download-URL: https://github.com/NASA-PDS/registry-sweepers/releases/
Author: PDS
Author-email: pds_operator@jpl.nasa.gov
License: apache-2.0
Keywords: pds,planetary data,registry
Classifier: Programming Language :: Python :: 3
Classifier: Programming Language :: Python :: 3.12
Classifier: Programming Language :: Python :: 3.13
Classifier: Operating System :: OS Independent
Requires-Python: >=3.12
License-File: LICENSE.md
License-File: NOTICE.txt
Requires-Dist: opensearch-py~=2.6
Requires-Dist: requests~=2.28
Requires-Dist: retry~=0.9.2
Requires-Dist: psutil~=5.9.7
Requires-Dist: pds.solr-to-es==0.3.0
Requires-Dist: tqdm~=4.66.2
Requires-Dist: boto3~=1.34.91
Requires-Dist: botocore~=1.34.91
Requires-Dist: botocore-stubs~=1.34.94
Requires-Dist: requests-aws4auth~=1.2.3
Requires-Dist: python-dateutil~=2.9.0
Requires-Dist: more-itertools~=10.8.0
Provides-Extra: dev
Requires-Dist: flake8~=7.3.0; extra == "dev"
Requires-Dist: flake8-bugbear~=24.12.12; extra == "dev"
Requires-Dist: flake8-docstrings~=1.7.0; extra == "dev"
Requires-Dist: pep8-naming~=0.13.3; extra == "dev"
Requires-Dist: mypy~=1.14.1; extra == "dev"
Requires-Dist: pydocstyle~=6.3.0; extra == "dev"
Requires-Dist: coverage~=7.3.0; extra == "dev"
Requires-Dist: pytest~=7.4.0; extra == "dev"
Requires-Dist: pytest-cov~=4.1.0; extra == "dev"
Requires-Dist: pytest-mock~=3.10; extra == "dev"
Requires-Dist: freezegun~=1.2; extra == "dev"
Requires-Dist: pytest-watch~=4.2.0; extra == "dev"
Requires-Dist: pytest-xdist~=3.3.1; extra == "dev"
Requires-Dist: pre-commit~=3.3.3; extra == "dev"
Requires-Dist: sphinx~=8.2.3; extra == "dev"
Requires-Dist: sphinx-rtd-theme~=3.0.2; extra == "dev"
Requires-Dist: types-python-dateutil==2.9.0.20241206; extra == "dev"
Requires-Dist: tox~=4.11.0; extra == "dev"
Requires-Dist: types-psutil~=5.9.5; extra == "dev"
Requires-Dist: types_requests~=2.28; extra == "dev"
Requires-Dist: types-retry~=0.9.9.4; extra == "dev"
Requires-Dist: types-setuptools~=68.1.0.0; extra == "dev"
Requires-Dist: types-tqdm~=4.66.0; extra == "dev"
Dynamic: download-url
Dynamic: license-file
